LICENSE
MANIFEST.in
README.md
requirements.txt
setup.cfg
setup.py
versioneer.py
intake_excel/__init__.py
intake_excel/_version.py
intake_excel/intake_excel.py
intake_excel.egg-info/PKG-INFO
intake_excel.egg-info/SOURCES.txt
intake_excel.egg-info/dependency_links.txt
intake_excel.egg-info/entry_points.txt
intake_excel.egg-info/not-zip-safe
intake_excel.egg-info/requires.txt
intake_excel.egg-info/top_level.txt