Metadata-Version: 2.1
Name: intake-excel
Version: 0.1.4
Summary: Excel plugin for Intake
Home-page: https://github.com/edjdavid/intake-excel
Maintainer: Eduardo David Jr
Maintainer-email: edjdavid@users.noreply.github.com
License: BSD
Platform: UNKNOWN
